dmf/__init__.py
dmf/__version__.py
dmf/alerts/__init__.py
dmf/alerts/__main__.py
dmf/alerts/alerts.py
dmf/alerts/backend.py
dmf/alerts/decorator.py
dmf/alerts/slack_backend.py
dmf/alerts/telegram_backend.py
dmf/env/__init__.py
dmf/env/env.py
dmf/io/__init__.py
dmf/io/compress.py
dmf/io/decompress.py
dmf/io/load.py
dmf/io/save.py
dmf/models/__init__.py
dmf/models/device.py
dmf/models/memory.py
dmf/models/seed.py
dmf/psy/__init__.py
dmf/psy/config.py
dmf/psy/dialog.py
dmf/psy/display.py
dmf/psy/distractors.py
dmf/psy/exceptions.py
dmf/psy/logger.py
dmf/psy/monitor.py
dmf/psy/screens.py
dmf/psy/trigger.py
dmf/utils/decorators.py
dmf/utils/format_bytes.py
dmf/utils/typing.py
dmf/video/__init__.py
dmf/video/video_reader.py
dmf/video/video_writer.py
dmf_utils-0.1.3.dist-info/LICENSE
dmf_utils-0.1.3.dist-info/METADATA
dmf_utils-0.1.3.dist-info/WHEEL
dmf_utils-0.1.3.dist-info/entry_points.txt
dmf_utils-0.1.3.dist-info/top_level.txt
dmf_utils-0.1.3.dist-info/RECORD
