Metadata-Version: 2.1
Name: dmf-utils
Version: 0.1.3
Summary: DMF's Python package providing reusable functionalities for neuroscience research.
Author-email: Dynamics of Memory Formation Group <llfuentemilla@ub.edu>, Pablo Marcos-Manchón <pmarcos@ub.edu>
License: MIT
Project-URL: repository, https://github.com/memory-formation/dmf-utils
Keywords: neuroscience,data analysis,research,python
Classifier: Development Status :: 4 - Beta
Classifier: Intended Audience :: Developers
Classifier: Intended Audience :: Science/Research
Classifier: License :: OSI Approved :: MIT License
Classifier: Natural Language :: English
Classifier: Operating System :: OS Independent
Classifier: Programming Language :: Python :: 3.7
Classifier: Programming Language :: Python :: 3.8
Classifier: Programming Language :: Python :: 3.9
Classifier: Programming Language :: Python :: 3.10
Classifier: Programming Language :: Python :: 3.11
Classifier: Programming Language :: Python :: 3.12
Classifier: Topic :: Scientific/Engineering :: Information Analysis
Classifier: Topic :: Software Development :: Libraries :: Python Modules
Requires-Python: >=3.7
License-File: LICENSE
Requires-Dist: lazy-loader
Requires-Dist: typing-extensions; python_version == "3.7"
Requires-Dist: python-dotenv<0.22.0,>=0.21.0; python_version == "3.7"
Requires-Dist: python-dotenv>=1.0.1; python_version >= "3.8"
Provides-Extra: alerts
Requires-Dist: slack-sdk; extra == "alerts"
Requires-Dist: requests; extra == "alerts"
Provides-Extra: all
Requires-Dist: sphinx; extra == "all"
Requires-Dist: pydata-sphinx-theme; extra == "all"
Requires-Dist: slack-sdk; extra == "all"
Requires-Dist: requests; extra == "all"
Requires-Dist: numpy; extra == "all"
Requires-Dist: opencv-python; extra == "all"
Requires-Dist: pillow; extra == "all"
Provides-Extra: docs
Requires-Dist: sphinx; extra == "docs"
Requires-Dist: pydata-sphinx-theme; extra == "docs"
Provides-Extra: extra
Requires-Dist: pandas; extra == "extra"
Requires-Dist: h5py; extra == "extra"
Requires-Dist: torch; extra == "extra"
Requires-Dist: pyyaml; extra == "extra"
Requires-Dist: scipy; extra == "extra"
Requires-Dist: librosa; extra == "extra"
Requires-Dist: matplotlib; extra == "extra"
Requires-Dist: py7zr; extra == "extra"
Provides-Extra: video
Requires-Dist: numpy; extra == "video"
Requires-Dist: opencv-python; extra == "video"
Requires-Dist: pillow; extra == "video"
